MANIFEST.in
README.md
setup.py
maki/__init__.py
maki/color.py
maki/maki.py
maki/contrib/__init__.py
maki/contrib/django.py
maki/img/marker-large.svg
maki/img/marker-small.svg
maki/img/icons/aerialway-11.svg
maki/img/icons/aerialway-15.svg
maki/img/icons/airfield-11.svg
maki/img/icons/airfield-15.svg
maki/img/icons/airport-11.svg
maki/img/icons/airport-15.svg
maki/img/icons/alcohol-shop-11.svg
maki/img/icons/alcohol-shop-15.svg
maki/img/icons/america-football-11.svg
maki/img/icons/america-football-15.svg
maki/img/icons/amusement-park-11.svg
maki/img/icons/amusement-park-15.svg
maki/img/icons/aquarium-11.svg
maki/img/icons/aquarium-15.svg
maki/img/icons/art-gallery-11.svg
maki/img/icons/art-gallery-15.svg
maki/img/icons/attraction-11.svg
maki/img/icons/attraction-15.svg
maki/img/icons/bakery-11.svg
maki/img/icons/bakery-15.svg
maki/img/icons/bank-11.svg
maki/img/icons/bank-15.svg
maki/img/icons/bar-11.svg
maki/img/icons/bar-15.svg
maki/img/icons/barrier-11.svg
maki/img/icons/barrier-15.svg
maki/img/icons/baseball-11.svg
maki/img/icons/baseball-15.svg
maki/img/icons/basketball-11.svg
maki/img/icons/basketball-15.svg
maki/img/icons/bbq-11.svg
maki/img/icons/bbq-15.svg
maki/img/icons/beer-11.svg
maki/img/icons/beer-15.svg
maki/img/icons/bicycle-11.svg
maki/img/icons/bicycle-15.svg
maki/img/icons/bicycle-share-11.svg
maki/img/icons/bicycle-share-15.svg
maki/img/icons/blood-bank-11.svg
maki/img/icons/blood-bank-15.svg
maki/img/icons/buddhism-11.svg
maki/img/icons/buddhism-15.svg
maki/img/icons/building-11.svg
maki/img/icons/building-15.svg
maki/img/icons/building-alt1-11.svg
maki/img/icons/building-alt1-15.svg
maki/img/icons/bus-11.svg
maki/img/icons/bus-15.svg
maki/img/icons/cafe-11.svg
maki/img/icons/cafe-15.svg
maki/img/icons/campsite-11.svg
maki/img/icons/campsite-15.svg
maki/img/icons/car-11.svg
maki/img/icons/car-15.svg
maki/img/icons/car-rental-11.svg
maki/img/icons/car-rental-15.svg
maki/img/icons/car-repair-11.svg
maki/img/icons/car-repair-15.svg
python_makiwich.egg-info/PKG-INFO
python_makiwich.egg-info/SOURCES.txt
python_makiwich.egg-info/dependency_links.txt
python_makiwich.egg-info/requires.txt
python_makiwich.egg-info/top_level.txt