Metadata-Version: 2.1
Name: python-makiwich
Version: 0.0.3
Summary: Create markers with maki icons for leaflet
Home-page: https://github.com/zostera/python-makiwich
Author: Jan Pieter Waagmeester
Author-email: jieter@zostera.nl
License: ISC
Keywords: Maki icon markers
Platform: UNKNOWN
Classifier: Intended Audience :: Developers
Classifier: License :: OSI Approved :: ISC License (ISCL)
Classifier: Programming Language :: Python :: 3
Classifier: Programming Language :: Python :: 3.6
Classifier: Programming Language :: Python :: 3.7
